Workbook

Sheet Sales_Data
A1: Order Date | B1: Order ID | C1: Region | D1: Category | E1: Product | F1: Customer Segment | G1: Quantity | H1: Unit Price | I1: Cost | J1: Sales | K1: Profit | L1: Profit Margin
A2: 46027 | B2: ORD001 | C2: North | D2: Electronics | E2: Laptop | F2: Consumer | G2: 2 | H2: 55000 | I2: 90000 | J2: =G2*H2 -> 110000 | K2: =J2-I2 -> 20000 | L2: =K2/J2 -> 0.18181818
A3: 46030 | B3: ORD002 | C3: South | D3: Accessories | E3: Mouse | F3: Corporate | G3: 10 | H3: 800 | I3: 5500 | J3: =G3*H3 -> 8000 | K3: =J3-I3 -> 2500 | L3: =K3/J3 -> 0.3125
A4: 46034 | B4: ORD003 | C4: West | D4: Electronics | E4: Headphones | F4: Consumer | G4: 5 | H4: 2500 | I4: 9000 | J4: =G4*H4 -> 12500 | K4: =J4-I4 -> 3500 | L4: =K4/J4 -> 0.28
A5: 46040 | B5: ORD004 | C5: East | D5: Furnitures | E5: Office Chair | F5: Corporate | G5: 3 | H5: 6500 | I5: 15000 | J5: =G5*H5 -> 19500 | K5: =J5-I5 -> 4500 | L5: =K5/J5 -> 0.23076923
A6: 46047 | B6: ORD005 | C6: North | D6: Electronics | E6: Monitor | F6: Consumer | G6: 4 | H6: 12000 | I6: 35000 | J6: =G6*H6 -> 48000 | K6: =J6-I6 -> 13000 | L6: =K6/J6 -> 0.27083333
A7: 46056 | B7: ORD006 | C7: South | D7: Electronics | E7: Keyboard | F7: Consumer | G7: 8 | H7: 1500 | I7: 8000 | J7: =G7*H7 -> 12000 | K7: =J7-I7 -> 4000 | L7: =K7/J7 -> 0.33333333
A8: 46063 | B8: ORD007 | C8: West | D8: Accessories | E8: Webcam | F8: Corporate | G8: 6 | H8: 2200 | I8: 9000 | J8: =G8*H8 -> 13200 | K8: =J8-I8 -> 4200 | L8: =K8/J8 -> 0.31818182
A9: 46070 | B9: ORD008 | C9: East | D9: Furnitures | E9: Desk | F9: Consumer | G9: 2 | H9: 9000 | I9: 13000 | J9: =G9*H9 -> 18000 | K9: =J9-I9 -> 5000 | L9: =K9/J9 -> 0.27777778
A10: 46078 | B10: ORD009 | C10: North | D10: Electronics | E10: Laptop | F10: Corporate | G10: 3 | H10: 55000 | I10: 135000 | J10: =G10*H10 -> 165000 | K10: =J10-I10 -> 30000 | L10: =K10/J10 -> 0.18181818
A11: 46086 | B11: ORD010 | C11: South | D11: Accessories | E11: Mouse | F11: Consumer | G11: 15 | H11: 800 | I11: 8000 | J11: =G11*H11 -> 12000 | K11: =J11-I11 -> 4000 | L11: =K11/J11 -> 0.33333333

Sheet Dashboard
A1: Retail Sales and Profitability Dashboard
A3: Total Sales | C3: Total Profit | E3: Profit Margin | G3: Total Orders | I3: Unit Sold
A4: =SUM(Sales_Data!J2:J11) -> 418200 | C4: =SUM(Sales_Data!K2:K11) -> 90700 | E4: =SUM(Sales_Data!K2:K11)/SUM(Sales_Data!J2:J11) -> 0.21688187 | G4: =COUNTA(Sales_Data!B2:B11) -> 10 | I4: =SUM(Sales_Data!G2:G11) -> 58
H6: Sales by region
A7: Monthly Sales and Profit data
H8: Region | I8: Sales
A9: Month | B9: Sales | C9: Profit | H9: North | I9: {=SUMPRODUCT(--(TRIM(Sales_Data!$C$2:$C$11)=TRIM(H9)),Sales_Data!$J$2:$J$11)} -> 323000
A10: January | B10: =SUMIFS(Sales_Data!$J$2:$J$11,Sales_Data!$A$2:$A$11,">="&DATE(2026,ROW()-9,1),Sales_Data!$A$2:$A$11,"<"&DATE(2026,ROW()-8,1)) -> 198000 | C10: =SUMIFS(Sales_Data!$K$2:$K$11,Sales_Data!$A$2:$A$11,">="&DATE(2026,ROW()-9,1),Sales_Data!$A$2:$A$11,"<"&DATE(2026,ROW()-8,1)) -> 43500 | H10: South | I10: {=SUMPRODUCT(--(TRIM(Sales_Data!$C$2:$C$11)=TRIM(H10)),Sales_Data!$J$2:$J$11)} -> 32000
A11: February | B11: =SUMIFS(Sales_Data!$J$2:$J$11,Sales_Data!$A$2:$A$11,">="&DATE(2026,ROW()-9,1),Sales_Data!$A$2:$A$11,"<"&DATE(2026,ROW()-8,1)) -> 208200 | C11: =SUMIFS(Sales_Data!$K$2:$K$11,Sales_Data!$A$2:$A$11,">="&DATE(2026,ROW()-9,1),Sales_Data!$A$2:$A$11,"<"&DATE(2026,ROW()-8,1)) -> 43200 | H11: East | I11: {=SUMPRODUCT(--(TRIM(Sales_Data!$C$2:$C$11)=TRIM(H11)),Sales_Data!$J$2:$J$11)} -> 37500
A12: March | B12: =SUMIFS(Sales_Data!$J$2:$J$11,Sales_Data!$A$2:$A$11,">="&DATE(2026,ROW()-9,1),Sales_Data!$A$2:$A$11,"<"&DATE(2026,ROW()-8,1)) -> 12000 | C12: =SUMIFS(Sales_Data!$K$2:$K$11,Sales_Data!$A$2:$A$11,">="&DATE(2026,ROW()-9,1),Sales_Data!$A$2:$A$11,"<"&DATE(2026,ROW()-8,1)) -> 4000 | H12: West | I12: {=SUMPRODUCT(--(TRIM(Sales_Data!$C$2:$C$11)=TRIM(H12)),Sales_Data!$J$2:$J$11)} -> 25700
A32: KEY INSIGHTS
A33: Highest Sales Month | B33: February — ₹208,200
A34: Lowest Sales Month | B34: March — ₹12,000
A35: Highest Sales Region | B35: North — ₹323,000
A36: Total Profit | B36: 90700
A37: Profit Margin | B37: 0.2169
